nekpy/__init__.py
nekpy/_version.py
nekpy/dask/__init__.py
nekpy/dask/metal.py
nekpy/dask/tasks.py
nekpy-0.0.1.dist-info/DESCRIPTION.rst
nekpy-0.0.1.dist-info/METADATA
nekpy-0.0.1.dist-info/RECORD
nekpy-0.0.1.dist-info/WHEEL
nekpy-0.0.1.dist-info/metadata.json
nekpy-0.0.1.dist-info/top_level.txt
nekpy-0.0.1.dist-info/zip-safe
