Metadata-Version: 2.0
Name: nekpy
Version: 0.0.1
Summary: Nek-related utilities in python
Home-page: http://github.com/maxhutch/nekpy/
Author: Max Hutchinson
Author-email: maxhutch@gmail.com
License: MIT
Keywords: nek5000
Platform: UNKNOWN
Requires-Dist: dask
